simfleet/__init__.py
simfleet/cli.py
simfleet/simulator.py
simfleet/strategies.py
simfleet/templates/index.html
simfleet/templates/assets/css/app.css
simfleet/templates/assets/css/bootstrap-treeview.min.css
simfleet/templates/assets/img/customer.png
simfleet/templates/assets/img/favicon-120.png
simfleet/templates/assets/img/favicon-152.png
simfleet/templates/assets/img/favicon-196.png
simfleet/templates/assets/img/favicon-76.png
simfleet/templates/assets/img/favicon.ico
simfleet/templates/assets/img/gasolinera.png
simfleet/templates/assets/img/station.png
simfleet/templates/assets/img/taxi.png
simfleet/templates/assets/img/taxi_busy.png
simfleet/templates/assets/img/taxi_free.png
simfleet/templates/assets/img/transport.png
simfleet/templates/assets/js/SidebarComponent.vue
simfleet/templates/assets/js/StatusIndicator.vue
simfleet/templates/assets/js/TreeView.vue
simfleet/templates/assets/js/main.js
simfleet/templates/assets/js/store.js
simfleet/templates/assets/js/app/app.js
simfleet/templates/assets/js/app/app.js.map
simfleet/templates/assets/node_modules/coa/coverage/index.html
simfleet/templates/assets/node_modules/coa/coverage/coa/index.html
simfleet/templates/assets/node_modules/coa/coverage/coa/index.js.html
simfleet/templates/assets/node_modules/coa/coverage/coa/lib/arg.js.html
simfleet/templates/assets/node_modules/coa/coverage/coa/lib/cmd.js.html
simfleet/templates/assets/node_modules/coa/coverage/coa/lib/coaobject.js.html
simfleet/templates/assets/node_modules/coa/coverage/coa/lib/coaparam.js.html
simfleet/templates/assets/node_modules/coa/coverage/coa/lib/color.js.html
simfleet/templates/assets/node_modules/coa/coverage/coa/lib/completion.js.html
simfleet/templates/assets/node_modules/coa/coverage/coa/lib/index.html
simfleet/templates/assets/node_modules/coa/coverage/coa/lib/index.js.html
simfleet/templates/assets/node_modules/coa/coverage/coa/lib/opt.js.html
simfleet/templates/assets/node_modules/coa/coverage/coa/lib/shell.js.html
simfleet-2.0.0.dist-info/AUTHORS.rst
simfleet-2.0.0.dist-info/LICENSE
simfleet-2.0.0.dist-info/METADATA
simfleet-2.0.0.dist-info/WHEEL
simfleet-2.0.0.dist-info/entry_points.txt
simfleet-2.0.0.dist-info/top_level.txt
simfleet-2.0.0.dist-info/RECORD
