Metadata-Version: 2.1
Name: simfleet
Version: 2.0.0
Summary: Agent-based fleet simulator to test strategies
Home-page: https://github.com/javipalanca/simfleet
Author: Javi Palanca
Author-email: jpalanca@dsic.upv.es
License: MIT license
Keywords: simfleet
Classifier: Development Status :: 4 - Beta
Classifier: Intended Audience :: Developers
Classifier: Intended Audience :: Education
Classifier: Intended Audience :: Science/Research
Classifier: Topic :: Scientific/Engineering :: Artificial Intelligence
Classifier: License :: OSI Approved :: MIT License
Classifier: Natural Language :: English
Classifier: Programming Language :: Python :: 3
Classifier: Programming Language :: Python :: 3.9
Classifier: Programming Language :: Python :: 3.10
Classifier: Programming Language :: Python :: 3.11
Classifier: Programming Language :: Python :: 3.12
License-File: LICENSE
License-File: AUTHORS.rst
Requires-Dist: Click (>=6.0)
Requires-Dist: spade (>=4.0.1)
Requires-Dist: pandas (>=0.25.3)
Requires-Dist: tabulate (>=0.8.2)
Requires-Dist: openpyxl (>=2.4.9)
Requires-Dist: urllib3 (>=1.26)
Requires-Dist: factory-boy (>=2.11.1)
Requires-Dist: requests (>=2.19.1)
Requires-Dist: geopy (>=1.17.0)
Requires-Dist: XlsxWriter (>=1.1.2)
Requires-Dist: loguru (>=0.3.2)
